{
    "1156884438769205369": {
        "name": "⭐﹒Premium Access",
        "description": "ยศ Premium ราคา 70",
        "price": 70,
        "roleId": 1203688560293838868,
        "emoji": "<a:i7:1210538764905087046>"
    },
    "1156884432553259068": {
        "name": "💙﹒Premium Access",
        "description": "ยศ Extra ราคา 300",
        "price": 300,
        "roleId": 1202220731505856532,
        "emoji": "<a:i7:1210538764905087046>"
    }
}

